emp_hooks/__init__.py
emp_hooks/handlers/__init__.py
emp_hooks/handlers/onchain/__init__.py
emp_hooks/handlers/onchain/event.py
emp_hooks/handlers/onchain/hooks.py
emp_hooks/handlers/scheduler/__init__.py
emp_hooks/handlers/scheduler/hooks.py
emp_hooks/handlers/scheduler/schedule.py
emp_hooks/handlers/sqs_hooks.py
emp_hooks/handlers/telegram/__init__.py
emp_hooks/handlers/telegram/hooks.py
emp_hooks/handlers/telegram/message.py
emp_hooks/handlers/twitter/__init__.py
emp_hooks/logger.py
emp_hooks/manager.py
emp_hooks/orm/__init__.py
emp_hooks/orm/base.py
emp_hooks/orm/engine.py
emp_hooks/orm/service.py
emp_hooks/py.typed
emp_hooks/types/__init__.py
emp_hooks/types/hook.py
emp_hooks/utils/__init__.py
emp_hooks/utils/aws/__init__.py
emp_hooks/utils/aws/dynamo.py
emp_hooks/utils/aws/queue.py
emp_hooks/utils/telegram.py
emp_hooks-0.0.12.post2.dist-info/METADATA
emp_hooks-0.0.12.post2.dist-info/WHEEL
emp_hooks-0.0.12.post2.dist-info/RECORD
