Metadata-Version: 2.3
Name: emp_hooks
Version: 0.0.12.post2
Summary: emp hooks
Author: johnny-emp
Author-email: johnny@empyrealsdk.com
Requires-Python: >=3.12
Classifier: Programming Language :: Python :: 3
Classifier: Programming Language :: Python :: 3.12
Classifier: Programming Language :: Python :: 3.13
Requires-Dist: alembic (>=1.12.0,<2.0.0)
Requires-Dist: boto3 (>=1.35.0,<2.0.0)
Requires-Dist: croniter (>=6.0.0,<7.0.0)
Requires-Dist: eth-rpc-py (>=0.1.29,<0.2.0)
Requires-Dist: pydantic (>=2.10.0,<3.0.0)
Requires-Dist: python-telegram-bot (>=21.0)
Requires-Dist: sqlalchemy (>=2.0.0,<3.0.0)
Requires-Dist: tweepy (>=4.15.0,<5.0.0)
Requires-Dist: websockets (>=15.0.0,<16.0.0)
